{
  "mod_version": "v1",

  "files": [
    {
      "name": "check-virtio.sh",
      "url": "https://raw.githubusercontent.com/Cartman25/redpill-virtio/master/src/check-virtio.sh",
      "sha256": "cb48b2fb508fce0b4ebdc3f9a4d16ef4d75a503e2a73637b9d678010ae330d70",
      "packed": false
    },

    {
      "name": "virtio-4.4.108-broadwell.tgz",
      "url": "https://github.com/jimmyGALLAND/redpill-ext/raw/master/virtio/releases/virtio-4.4.108-broadwell.tgz",
      "sha256": "2d7a1bec86a277ce9a6c64ab7b66783554740599655b77e6064fe46ef94144f4",
      "packed": true
    }
  ],

  "kmods": {
    "virtio.ko": "",
    "virtio_ring.ko": "",
    "virtio_mmio.ko": "",
    "virtio_pci.ko": "",
    "virtio_blk.ko": "",
    "virtio_net.ko": "",
    "virtio_scsi.ko": "",
    "virtio_balloon.ko": ""
  },

  "scripts": {
    "check_kmod": "check-virtio.sh"
  }
}
